Workbook

Sheet 说明
A1: 主力净流入策略 V4.1 评审与回测方案(Excel 配套)
A3: 对象 | B3: V4.1 每日选股报告 2026-10-09(候选池 387 只、观察 60 只、0 买入)及其 Excel
A4: 本工作簿 | B4: 问题清单(15 项,按严重度)→ V4.1→V4.2 对照 → 实验矩阵 E1~E9 → 数据字典 → 参数网格 → 成本模型(公式)→ 验收门槛(公式判定)→ 结果登记 → 路线图 → 本地 Claude Code 清单
A5: 使用 | B5: 浅黄=可改输入;浅蓝=公式输出。本地回测跑完后,把关键数字填入《结果登记》,《验收门槛》自动给出 PASS/FAIL。
A6: 代码 | B6: backtest/ 目录:bt 包、selftest.py、run_backtest.py、config.example.yaml、CLAUDE_CODE_TASK.md
A7: 重要提示 | B7: 合成数据自检结果只证明引擎无前视/无技术错误,不是 V4.1 或 V4.2 的收益证据。阈值(G1~G4)是预先登记的建议值,可按你的风险偏好调整,但必须在看到样本外结果之前确定。仅供研究,不构成投资建议。

Sheet 问题清单
A1: V4.1 问题清单(按严重度排序)
A3: 编号 | B3: 严重度 | C3: 模块 | D3: 问题 | E3: 证据(来自 10-09 报告/Excel) | F3: 影响 | G3: 调整措施 | H3: 验证实验
A4: P1 | B4: 致命 | C4: 验证 | D4: 没有任何样本外业绩证据 | E4: 方案 2026-08-12 定稿;至 2026-10-09 仅 60 个交易日试运行;C1 绝对门槛(需≥60 个历史样本)直到本期才勉强接近,期间 0 买入;跟踪表只回填观察名单,无全市场对照 | F4: 无法回答"这个策略是否赚钱、赚多少、风险多大";所有参数(35/25/20/20、1.5、15%)均未经检验 | G4: 先对全市场做历史回测与 IC 检验(≥2 年),再决定是否继续迭代评分;同时建立不可修改的前向记录 | H4: E1,E2,E8
A5: P2 | B5: 致命 | C5: 信号 | D5: 核心因子"主力净流入"的预测力未被检验 | E5: 初筛、D1、D2、C4 全部围绕主力净流入;资金由数据商按单笔成交额阈值划分,买卖必有对手方;5 日累计、当日值均为顺周期的成交结果 | F5: 该类指标在 A 股 1~5 日常呈"延续与反转并存",随市值、换手、行情风格切换;若无稳定 IC,整个体系只是在给"当日强势股"排序 | G5: 对资金类因子做 1/3/5/10/20 日 RankIC、分层收益、行业市值中性检验;区分净流入占成交额、相对自身历史的异常程度、连续性 | H5: E1
A6: P3 | B6: 严重 | C6: 评分 | D6: 四维分高度共线,名义 4 维实为约 2.5 维 | E6: 候选池 387 只:D1 与 资金/市值比 的 Spearman ρ=0.97;D1–D2 ρ=0.83;相关矩阵参与比≈2.5;D1 贡献原始分方差约 44%(名义权重 35%),D4 仅约 11%(名义 20%) | F6: 权重与"四维均衡"的叙述不符;C3 只检验离散度(标准差>0.05),不检验独立性与预测力,形同虚设 | G6: 改为:先做相关性/VIF 筛选,再用滚动 IC 或岭回归定权重;C3 换为"相关矩阵条件数/有效维度"检查 | H6: E1,E2
A7: P4 | B7: 严重 | C7: 评分 | D7: 动量与反转混在同一个分数里(U 型) | E7: 修正综合分按当日涨跌幅五分位:最跌 20% 为 4.20、中间 3.54~3.75、最涨 20% 为 4.88;D4(距压力位空间)与涨跌幅 ρ=-0.30;观察第 1 名胜通能源当日-8.23%、5 日-17.41% | F7: D4"跌透反弹加分"与低 BIAS20 降低 Overheat 同向奖励下跌,与"资金动量"逻辑冲突;组合同时持有接飞刀与追涨两类风险 | G7: 拆为两个子策略:动量延续(资金流入+趋势向上)与超跌吸筹(资金流入+超跌),各自评分、各自回测,不混合 | H7: E4
A8: P5 | B8: 严重 | C8: 评分 | D8: 维度分与双门槛全部"批内相对化" | E8: 维度分=0.5×批内Z排名+0.5×批内分位(历史分位"暂以批内替代");初筛 N 历史在 662~1682 之间波动(今日 1432);相对条件为前 15% | F8: 分数分布由构造决定(近似均匀),不含绝对强弱信息;牛熊切换、资金面整体放量/缩量时无法区分"好日子"与"坏日子" | G8: 加入时间序列维度(相对自身 60/120 日的异常程度)、行业/市值中性残差;绝对条件改用"预期超额收益模型输出"而非历史综合分分位 | H8: E1,E4
A9: P6 | B9: 严重 | C9: 熔断 | D9: C1 绝对门槛设计缺陷;C2/C3 为恒真或弱检验 | E9: C1:绝对条件=历史综合分 60 分位,但综合分本身是批内排名构造,分布近似稳定→"绝对门槛"几乎不含信息,即使攒够 250 天也只会退化为纯相对;C2:Overheat 已 min-max 归一,值域必然∈[0,1] | F9: 熔断触发=0 买入但并不降低真实风险;熔断通过也不代表策略有效(无法证伪) | G9: 删除 C1/C2 形式熔断,换成真实熔断:数据熔断(缺失率、单位、N 异常)、环境闸门(敞口 0~100%)、策略回撤熔断(滚动 20 日净值)、容量熔断 | H9: E6
A10: P7 | B10: 严重 | C10: 过热惩罚 | D10: Overheat 惩罚近乎装饰 | E10: 修正分=原始分-1.5×Overheat;Overheat 标准差 0.119,惩罚的截面波动仅≈0.18,而原始分标准差 1.25;前 60 名在有无惩罚下重合 54/60;Overheat 与当日涨跌幅 ρ 为正、与 D4 ρ=-0.49 | F10: 既没挡住追高(涨停硬约束才是真正的约束),又与 D4 反向相互抵消;系数 1.5 无来源 | G10: 取消减法惩罚;用硬过滤(5 日涨幅区间 -12%~+25%、涨停不买、BIAS20 上限)替代;如保留则用回测定系数 | H10: E2
A11: P8 | B11: 严重 | C11: 初筛 | D11: 816/1432(57%)"主力与散户同为净流入"被当作口径异常剔除 | E11: [4] 剔除 816 只;C5 损耗率 58.7%,报告自己承认"样本存在轻度选择性偏差" | F11: 中单/对手盘为净流出时,主力与小单同为净流入完全可能;该规则实际引入了隐含因子(主力买、散户卖)并大幅改变样本,且未经检验 | G11: 不剔除,改为特征 retail_div=(主力-小单)/成交额,检验是否有增量;如有效再作为打分项 | H11: E2
A12: P9 | B12: 严重 | C12: 闸门 | D12: 宏观闸门阈值几乎永远不会触发,且缺少 A 股内生状态变量 | E12: 触发条件=沪深300/中证500 单日跌>5%、美国 CPI/非农/FOMC 日、重大政策;本期各项均"未触发" | F12: 单日-5% 在 A 股极为罕见,事件日历只提示波动而非方向;真正决定该策略胜率的广度、成交额、风格、跌停家数等未纳入 | G12: 改为 5 项环境分(广度、成交额分位、指数趋势、跌停占比、波动率分位)→ 敞口 0/25/50/75/100%;阈值由回测校准 | H12: E6
A13: P10 | B13: 中 | C13: 执行 | D13: 没有持有期、退出、仓位规则,T+1 与交易成本未建模 | E13: 报告只有"观察"与 T+1/T+5/T+10 回填;组合约束仅有行业≤2 只/单票≤15%/权重≤40%;成本"0 元" | F13: 无法计算净收益;A 股 T+1、涨跌停、停牌、滑点、冲击会显著吞噬短线资金流策略的收益 | G13: T 收盘出信号→T+1 开盘成交(涨停不买);持有 N 日 + 7%止损 + 资金流反转离场;10~20 只、单票≤10%、行业≤30%;成本按双边≥0.3% 起算并做敏感性 | H13: E3,E5
A14: P11 | B14: 中 | C14: 评分 | D14: 压力位数据缺省被当成利好,且空间指标逻辑矛盾 | E14: 华鑫股份"压力位数据缺省(space=0)"却列为 D4 贡献维度 9.0;汉得信息距压力位 2.31%、TCL 中环 0.52% 仍高分入围 | F14: 缺省值处理可能把"无数据"当作"无压力";近压力位的高分标的盈亏比不足 | G14: 缺省→剔除或中性分,不得加分;D4 改为盈亏比(ATR 止损距离 vs 压力位距离),盈亏比<1.5 直接排除 | H14: E2,E4
... A18: P15 | B18: 低 | C18: 初筛 | D18: 换手 1%~5%、市值 30~500 亿等硬边界未经检验 | E18: 硬边界剔除大量强势股与大盘股 | F18: 边界附近样本可能系统性不同;参数悬崖 | G18: 做边界敏感性(0.5%/8% 换手、20/800 亿市值) | H18: E3

Sheet V4.1→V4.2
A1: 调整方案对照
A3: 领域 | B3: V4.1 现状 | C3: V4.2 调整 | D3: 理由
A4: 样本与验证 | B4: 仅观察名单跟踪,无历史回测 | C4: 全市场 ≥2 年历史:单因子 IC → 分层 → 组合回测 → 样本外一次性验证 | D4: 没有证据的参数不应上线
A5: 信号构造 | B5: 资金/市值比为核心(D1≈该因子) | C5: 资金流改为"净流入占成交额"、5/20 日平滑、相对自身 60 日历史的 z 值、连续净流入天数;资金/市值比仅作对照 | D5: 去市值相关性,保留异常程度与持续性
A6: 维度结构 | B6: 四维、权重 35/25/20/20、批内 Z+分位 | C6: 按 IC/岭回归滚动定权重;截面分位→行业市值中性;剔除共线因子 | D6: 有效维度从 2.5 提升到可解释的 3~4
A7: 动量/反转 | B7: 同一分数里混合 | C7: 两个子策略:mom(资金流入+站上20日线)与 rev(资金流入+超跌),分别回测 | D7: 避免 U 型分数与风险暴露不清
A8: 过热惩罚 | B8: 原始分-1.5×Overheat | C8: 取消减法;硬过滤:5日涨幅∈[-12%,+25%]、涨停不买、剔除新股/ST | D8: 惩罚近乎装饰,硬过滤更可控
A9: [4] 同向剔除 | B9: 剔除 57% 样本 | C9: 不剔除;retail_div 作为候选因子检验 | D9: 避免隐含因子与选择性偏差
A10: 双门槛/C1 | B10: 前15%+历史 60 分位 | C10: 前 N 名(10~20)+ 预期超额模型阈值;C1/C2 删除 | D10: 绝对门槛在批内构造下无信息
A11: 宏观闸门 | B11: 单日-5% / 海外事件 / 政策 | C11: 5 项 A 股环境分 → 敞口 0~100%;事件日只降杠杆不改方向 | D11: 更贴合 A 股状态
A12: 买卖点与持有 | B12: 未定义 | C12: T+1 开盘买(涨停不买);持有 N 日(E3 定);7% 止损或 ATR 止损;资金流 5 日转负离场 | D12: 可计算净收益与回撤
A13: 组合约束 | B13: 行业≤2 只/单票≤15%/权重≤40% | C13: 10~20 只、单票≤10%、行业≤30%、单票≤20 日成交额 5% | D13: 分散与容量
A14: 成本 | B14: 报告 0 元 | C14: 佣金万2.5×2、印花税 0.05%(卖)、过户费 0.001%、滑点≥10bp+冲击 | D14: 净值口径
... A17: 评估闭环 | B17: T+1/T+5/T+10 回填(仅观察名单) | C17: 全池信号登记 + 与基准/随机组合对比 + 滚动 IC 监控 + 衰减报警 | D17: 能发现因子失效

Sheet 实验矩阵
A1: 回测实验矩阵 E1~E9
A3: 编号 | B3: 实验 | C3: 要回答的问题 | D3: 预先登记的假设 | E3: 配置 | F3: 输出指标 | G3: 通过标准 | H3: 代码入口
A4: E1 | B4: 单因子体检 | C4: V4.1 各维度与候选因子是否有预测力 | D4: H1:资金占成交额比的 5 日 RankIC>0.02;H2:V4.1 修正综合分在中性化后 IC 显著低于其子因子;H3:D3/D4 的 IC 为负或不显著 | E4: 全市场(30~500亿、非ST、上市>120日);horizons=1/3/5/10/20;原始 vs 行业+市值中性 | F4: IC 均值、ICIR、Newey-West t、IC 正占比、五分层多空、单调性 | G4: 中性后 5 日 RankIC≥0.02 且 NW-t≥2.5、单调性≥0.7 | H4: experiments.E1_factor_ic
A5: E2 | B5: V4.1 复刻与组件消融 | C5: 每个组件是正贡献还是负贡献 | D5: H4:去掉 Overheat 几乎无变化;H5:去掉 D4 改善;H6:去掉[4]剔除改善;H7:前15%→前30% 改善 | E5: 基线+9 个变体;持有5日、止损7%、Top10 | F5: 年化、夏普、回撤、胜率、盈亏比、笔数 | G5: 识别"负贡献组件"(去掉后夏普提升>0.1) | H5: experiments.E2_baseline_ablation
A6: E3 | B6: 持有期/止损/TopN 网格 | C6: 收益来自哪个持有期;参数是否有平台区 | D6: H8:3~10 日最优;H9:止损 5~8% 改善回撤 | E6: hold∈{1,3,5,10,20}×stop∈{无,5%,8%,12%}×TopN∈{5,10,20} | F6: 热力图;相邻参数夏普均值/中位 | G6: 最优点邻域(±1 档)夏普≥最优的 70%(无尖峰) | H6: experiments.E3_hold_stop_grid
A7: E4 | B7: V4.2 变体 | C7: 动量/反转拆分、中性化、因子集合 | D7: H10:拆分后 mom 子策略回撤低于 V4.1;H11:中性化降低风格暴露 | E7: 6 个变体 + V4.1 对照 | F7: 同上 + 平均敞口 | G7: 优于 V4.1 且回撤更小 | H7: experiments.E4_v42_variants
A8: E5 | B8: 成本与容量 | C8: 净收益在现实成本下是否存活 | D8: H12:滑点 20bp 时超额仍为正 | E8: 滑点 0/5/10/20/30bp × 资金 500万/5000万/2亿/10亿 | F8: 净年化、夏普、换手 | G8: 滑点20bp 下年化超额≥6% | H8: experiments.E5_costs_capacity
A9: E6 | B9: 环境闸门 | C9: 闸门是否真的降回撤 | D9: H13:闸门降低最大回撤≥20% 且收益损失<30% | E9: 无/默认/严格/宽松四档 | F9: 回撤、夏普、敞口 | G9: 回撤改善且夏普不降 | H9: experiments.E6_gate
A10: E7 | B10: 滚动样本外 | C10: 参数选择流程本身是否稳健 | D10: H14:训练期选优参数在测试期保持正超额 | E10: 训练250日/测试60日;候选=持有期×止损×TopN | F10: 拼接样本外净值;通缩夏普概率 | G10: 样本外夏普≥0.6×样本内,DSR概率≥0.9 | H10: experiments.E7_walk_forward
A11: E8 | B11: 样本内/外与自助法 | C11: 冻结规则后的最终检验(只看一次) | D11: H15:2026-01-05 起样本外超额>0 | E11: 样本外=2026-01-05~最新;块自助法 300 次 | F11: 夏普 5/95 分位、超额 t 值 | G11: 夏普5分位>0 或超额t>2 | H11: experiments.E8_oos_split
A12: E9 | B12: 安慰剂与信号延迟 | C12: 收益是否来自信号而非机制/运气 | D12: H16:随机打乱得分得不到同等收益;延迟1日仍保留≥50% 超额 | E12: 20 次同日随机打乱;延迟 1/2/3 日 | F12: 真实 vs 随机 95 分位;衰减曲线 | G12: 真实年化>随机 95 分位;延迟1日保留≥50% | H12: experiments.E9_placebo_delay

Sheet 数据字典
A1: 数据字典与点时(PIT)规则
A3: 表 | B3: 字段 | C3: 单位 | D3: 点时规则 | E3: 检验
A4: 日K | B4: date,code | C4: - | D4: 按交易日对齐;含退市、ST、停牌记录 | E4: 股票数应远大于现存 A 股数;停牌日 volume=0
A5: 日K | B5: open/high/low/close | C5: 元 | D5: 未复权价用于涨跌停/成交判断;复权价用于收益 | E5: 涨跌幅>25% 占比≈0(排除新股首日)
A6: 日K | B6: adj_factor | C6: - | D6: 后复权累计因子;缺失则全 1 | E6: 除权日前后收益连续
A7: 日K | B7: volume/amount | C7: 股/元 | D7: amount 用于 20 日均成交额与容量 | E7: amount≈volume×均价
A8: 日K | B8: turnover | C8: % | D8: 与所用市值口径一致(流通) | E8: 1%~5% 区间占比合理
A9: 日K | B9: mktcap | C9: 亿元 | D9: T 日收盘后可得;流通市值 vs 总市值须与实盘一致 | E9: 不得用最新市值回填历史
A10: 日K | B10: is_st/susp | C10: bool | D10: 按当日状态(历史 ST 标记),不是现状 | E10: 回测中 ST 样本占比随年份变化
A11: 资金流 | B11: main_net | C11: 元 | D11: T 日收盘终值;口径(大单阈值)全历史一致 | E11: |main_net|≤amount;与 small_net 符号分布合理
A12: 资金流 | B12: small_net | C12: 元 | D12: 散户代理(小单);与实盘一致 | E12: -
A13: 行业 | B13: sw_l1 | C13: - | D13: 点时申万一级;至少用最新分类并标注 | E13: 无大量"未知"
A14: 指数 | B14: close | C14: 点 | D14: 沪深300/中证500/中证1000/等权全A | E14: 用于闸门与基准

Sheet 参数网格
A1: 参数网格
A3: 参数 | B3: 取值 | C3: 实验
A4: 持有隔夜数 hold | B4: 1,3,5,10,20 | C4: E3/E7
A5: 止损 stop_loss | B5: 无,5%,8%,12% | C5: E3/E7
A6: TopN | B6: 5,10,20 | C6: E3/E7
A7: 行业上限 ind_cap | B7: 2,3 | C7: E4
A8: 相对门槛 top_pct(V4.1) | B8: 5%,15%,30% | C8: E2
A9: Overheat 系数 | B9: 0,1.5,3.0 | C9: E2
A10: 滑点 bp | B10: 0,5,10,20,30 | C10: E5
A11: 资金规模 | B11: 500万,5000万,2亿,10亿 | C11: E5
A12: 闸门广度阈值 | B12: 25%,35%,45% | C12: E6
A13: 5 日涨幅过滤 | B13: [-12%,+25%],[-8%,+15%],无 | C13: E4(扩展)

Sheet 成本模型
A1: 交易成本模型(可改黄色单元格)
A3: 佣金(单边) | B3: 0.00025
A4: 印花税(仅卖出) | B4: 0.0005
A5: 过户费(单边) | B5: 1e-05
A6: 滑点(单边,bp) | B6: 10
A7: 冲击系数(bp/参与率) | B7: 10
A8: 参与率(下单额/20日成交额) | B8: 0.02
A9: 年换手(单边,倍) | B9: 40
A10: 毛年化收益(假设) | B10: 0.25
A12: 往返成本(%) | B12: =2*B3+B4+2*B5+2*B6/10000+2*B7*B8/10000
A13: 年化成本拖累(%) | B13: =B12*B9/2
A14: 净年化收益(%) | B14: =B10-B13
A15: 盈亏平衡毛收益/笔(%) | B15: =B12
A17: 解读:往返成本≈0.3~0.5%;若平均持有 5 日、年换手 40 倍,成本拖累可达 6~10%/年——这是资金流类短线策略最常被忽略的利润侵蚀。

Sheet 结果登记
A1: 结果登记(本地回测完成后填写黄色单元格)
A3: 指标 | B3: 取值 | C3: 来源
A4: V4.1 修正综合分:5日RankIC(中性) | C4: E1
A5: V4.1 修正综合分:NW-t | C5: E1
A6: V4.2 核心因子:5日RankIC(中性) | C6: E1
A7: V4.2 核心因子:NW-t | C7: E1
A8: V4.2 五分层单调性 | C8: E1
A9: V4.1 样本内夏普 | C9: E8
A10: V4.1 样本外夏普 | C10: E8
A11: V4.2 样本内夏普 | C11: E8
A12: V4.2 样本外夏普 | C12: E8
A13: V4.2 滑点20bp年化超额 | C13: E5
A14: V4.2 最大回撤 | C14: E8/E4
A15: V4.2 通缩夏普概率 | C15: E7
... A22: 总试验次数 | C22: trials.csv

Sheet 验收门槛
A1: 预先登记的验收门槛(阈值可改;必须在看到样本外结果之前确定)
A3: 编号 | B3: 名称 | C3: 指标 | D3: 阈值 | E3: 本次取值 | F3: 结论 | G3: 说明
A4: G1 | B4: 因子有效 | C4: V4.2 核心因子 5 日 RankIC(行业市值中性) | D4: 0.02 | E4: =IF(COUNT(结果登记!$B$6)<1,"",结果登记!$B$6) | F4: =IF(E4="","待填",IF(E4>=D4,"PASS","FAIL")) | G4: 且 NW-t≥2.5、五分层单调性≥0.7
A5: G2 | B5: 样本外一致 | C5: 样本外夏普 ÷ 样本内夏普 | D5: 0.6 | E5: =IF(COUNT(结果登记!$B$11,结果登记!$B$12)<2,"",结果登记!$B$12/结果登记!$B$11) | F5: =IF(E5="","待填",IF(E5>=D5,"PASS","FAIL")) | G5: 同口径、规则冻结后
A6: G3 | B6: 成本后盈利 | C6: 滑点 20bp 下年化超额(相对基准) | D6: 0.06 | E6: =IF(COUNT(结果登记!$B$13)<1,"",结果登记!$B$13) | F6: =IF(E6="","待填",IF(E6>=D6,"PASS","FAIL")) | G6: 基准=中证500/1000 等权混合
A7: G4a | B7: 风险 | C7: 最大回撤上限 | D7: -0.2 | E7: =IF(COUNT(结果登记!$B$14)<1,"",结果登记!$B$14) | F7: =IF(E7="","待填",IF(E7>=D7,"PASS","FAIL")) | G7: 组合口径,含止损与闸门
A8: G4b | B8: 统计显著 | C8: 通缩夏普概率 | D8: 0.9 | E8: =IF(COUNT(结果登记!$B$15)<1,"",结果登记!$B$15) | F8: =IF(E8="","待填",IF(E8>=D8,"PASS","FAIL")) | G8: 用全部试验次数折扣
A9: G4c | B9: 安慰剂 | C9: 真实年化 − 随机打乱95分位 > 0 | D9: 0 | E9: =IF(COUNT(结果登记!$B$16,结果登记!$B$17)<2,"",结果登记!$B$16-结果登记!$B$17) | F9: =IF(E9="","待填",IF(E9>=D9,"PASS","FAIL")) | G9: E9
A10: G4d | B10: 信号延迟 | C10: 延迟1日保留的超额比例 | D10: 0.5 | E10: =IF(COUNT(结果登记!$B$18,结果登记!$B$19)<2,"",结果登记!$B$18/结果登记!$B$19) | F10: =IF(E10="","待填",IF(E10>=D10,"PASS","FAIL")) | G10: E9
A11: G4e | B11: 参数平台 | C11: 邻域夏普 ÷ 最优夏普 | D11: 0.7 | E11: =IF(COUNT(结果登记!$B$20,结果登记!$B$21)<2,"",结果登记!$B$21/结果登记!$B$20) | F11: =IF(E11="","待填",IF(E11>=D11,"PASS","FAIL")) | G11: E3
C13: 综合结论 | F13: =IF(COUNTIF(F4:F11,"待填")>0,"待填",IF(COUNTIF(F4:F11,"FAIL")=0,"可进入前向模拟盘","不通过"))
C14: 规则:全部 PASS 才建议进入≥3 个月前向模拟盘;任一 FAIL 回到 E1/E2 找根因,不得放宽阈值。

Sheet 路线图
A1: 实施路线图
A3: 周 | B3: 里程碑 | C3: 产出 | D3: 负责
A4: 第1周 | B4: 数据摸底与口径对齐 | C4: db_schema.md、config.yaml、数据体检通过、V41_HOOK 对齐(前60名重合≥95%) | D4: 本地 Claude Code + 你
A5: 第2周 | B5: E1 单因子体检 + E2 消融 | C5: 因子有效性结论;负贡献组件清单;是否继续的决策点 | D5: 本地 Claude Code
A6: 第3周 | B6: E3~E6 | C6: 持有期/止损平台区、V4.2 变体、成本容量、环境闸门 | D6: 本地 Claude Code
A7: 第4周 | B7: E7 滚动样本外、规则冻结 | C7: 冻结版 V4.2 规格书;试验次数登记 | D7: 你 + 投研评审
A8: 第5周 | B8: E8 样本外一次性检验 + E9 | C8: 验收门槛 PASS/FAIL;回测报告 | D8: 本地 Claude Code
A9: 第6~18周 | B9: 前向模拟盘(≥3 个月) | C9: 每日信号登记、滚动 IC、衰减报警;与回测偏差<阈值才可小仓实盘 | D9: 你

Sheet 本地Claude Code清单
A1: 本地 Claude Code 执行清单(勾选)
A3: # | B3: 任务 | C3: 完成标准 | D3: 完成?
A4: 1 | B4: 摸清数据库结构,写 db_schema.md | C4: 日K/资金流/行业/指数的表、列、单位、区间、是否含退市股
A5: 2 | B5: 填 config.yaml,单位核对为 亿元/元 | C5: 数据体检各项达标
A6: 3 | B6: 封装生产评分为 V41_HOOK | C6: 5 个历史日前60名重合≥95%
A7: 4 | B7: selftest.py 全部 PASS;真实数据截断不变性 | C7: 无前视证明
A8: 5 | B8: E1 → 决策点 | C8: 输出因子体检表;若 V4.1 综合分无预测力,先停下汇报
A9: 6 | B9: E2~E6 | C9: 输出各表与净值图
A10: 7 | B10: E7 滚动样本外,记录试验次数 | C10: trials.csv
A11: 8 | B11: 冻结规则,运行 E8/E9(样本外只看一次) | C11: 回测报告.md + 验收门槛填表
A12: 9 | B12: 回写《结果登记》 | C12: 验收门槛得出综合结论
